argparse_dantic/__init__.py
argparse_dantic/_argparse/__init__.py
argparse_dantic/_argparse/actions.py
argparse_dantic/_argparse/container.py
argparse_dantic/_argparse/help.py
argparse_dantic/_argparse/parser.py
argparse_dantic/dantic_types/__init__.py
argparse_dantic/dantic_types/_construct.py
argparse_dantic/dantic_types/_fields.py
argparse_dantic/dantic_types/_import_utils.py
argparse_dantic/dantic_types/fields.py
argparse_dantic/dantic_types/main.py
argparse_dantic/parsers/__init__.py
argparse_dantic/parsers/boolean.py
argparse_dantic/parsers/command.py
argparse_dantic/parsers/container.py
argparse_dantic/parsers/enum.py
argparse_dantic/parsers/literal.py
argparse_dantic/parsers/mapping.py
argparse_dantic/parsers/standard.py
argparse_dantic/utils/__init__.py
argparse_dantic/utils/arguments.py
argparse_dantic/utils/errors.py
argparse_dantic/utils/namespaces.py
argparse_dantic/utils/pydantic.py
argparse_dantic/utils/types.py
argparse_dantic-0.0.0.dist-info/licenses/LICENSE
argparse_dantic-0.0.0.dist-info/METADATA
argparse_dantic-0.0.0.dist-info/WHEEL
argparse_dantic-0.0.0.dist-info/top_level.txt
argparse_dantic-0.0.0.dist-info/RECORD
