Metadata-Version: 2.4
Name: argparse-dantic
Version: 0.0.0
Summary: Typed Argument Parsing with Pydantic enhanced version
Author-email: Erlone Alpha <zhongerlong@gmail.com>
License-Expression: MIT
Project-URL: Changelog, https://github.com/Erlonealpha/argparse-dantic/blob/master/CHANGELOG.md
Project-URL: Repository, https://github.com/Erlonealpha/argparse-dantic
Project-URL: Issues, https://github.com/Erlonealpha/argparse-dantic/issues
Keywords: python,pydantic,argparse,typed,validation
Classifier: Development Status :: 4 - Beta
Classifier: Programming Language :: Python
Classifier: Programming Language :: Python :: 3.10
Classifier: Programming Language :: Python :: 3.11
Classifier: Programming Language :: Python :: 3.12
Classifier: Programming Language :: Python :: 3.13
Classifier: Intended Audience :: Developers
Classifier: Framework :: Pydantic
Classifier: Topic :: Software Development :: Libraries :: Python Modules
Requires-Python: >=3.10
License-File: LICENSE
Requires-Dist: pydantic>=2.10.0
Requires-Dist: rich>=12.0.0
Dynamic: license-file
